{
"type": "FeatureCollection",
"crs": { "type": "name", "properties": { "name": "urn:ogc:def:crs:OGC:1.3:CRS84" } },
                                                                                
"features": [
{ "type": "Feature", "properties": { "id": 1 }, "geometry": { "type": "Point", "coordinates": [ -84.148185806682392, 9.943080267352778 ] } },
{ "type": "Feature", "properties": { "id": 5 }, "geometry": { "type": "Point", "coordinates": [ -84.1362943899382, 9.918305100647352 ] } },
{ "type": "Feature", "properties": { "id": 4 }, "geometry": { "type": "Point", "coordinates": [ -84.136337513842989, 9.917402412369105 ] } },
{ "type": "Feature", "properties": { "id": 3 }, "geometry": { "type": "Point", "coordinates": [ -84.136617819224085, 9.915788187131527 ] } },
{ "type": "Feature", "properties": { "id": 2 }, "geometry": { "type": "Point", "coordinates": [ -84.136704067033648, 9.915289050086935 ] } },
{ "type": "Feature", "properties": { "id": 6 }, "geometry": { "type": "Point", "coordinates": [ -84.141835811702975, 9.912931413773071 ] } },
{ "type": "Feature", "properties": { "id": 7 }, "geometry": { "type": "Point", "coordinates": [ -84.141986745369735, 9.91659530074417 ] } },
{ "type": "Feature", "properties": { "id": 12 }, "geometry": { "type": "Point", "coordinates": [ -84.142116117084115, 9.922075124808101 ] } },
{ "type": "Feature", "properties": { "id": 11 }, "geometry": { "type": "Point", "coordinates": [ -84.142202364893677, 9.921246785190464 ] } },
{ "type": "Feature", "properties": { "id": 10 }, "geometry": { "type": "Point", "coordinates": [ -84.142450327346168, 9.920460922591289 ] } },
{ "type": "Feature", "properties": { "id": 9 }, "geometry": { "type": "Point", "coordinates": [ -84.14266594687011, 9.919611339282358 ] } },
{ "type": "Feature", "properties": { "id": 8 }, "geometry": { "type": "Point", "coordinates": [ -84.142698289798702, 9.91868741493321 ] } },
{ "type": "Feature", "properties": { "id": 15 }, "geometry": { "type": "Point", "coordinates": [ -84.142245488798437, 9.924793763191145 ] } },
{ "type": "Feature", "properties": { "id": 14 }, "geometry": { "type": "Point", "coordinates": [ -84.142148460012677, 9.923806135451166 ] } },
{ "type": "Feature", "properties": { "id": 13 }, "geometry": { "type": "Point", "coordinates": [ -84.141911278536369, 9.922882222933451 ] } },
{ "type": "Feature", "properties": { "id": 19 }, "geometry": { "type": "Point", "coordinates": [ -84.132607296079186, 9.916436002162266 ] } },
{ "type": "Feature", "properties": { "id": 18 }, "geometry": { "type": "Point", "coordinates": [ -84.133771641508346, 9.920152948896387 ] } },
{ "type": "Feature", "properties": { "id": 17 }, "geometry": { "type": "Point", "coordinates": [ -84.133987261032274, 9.922085744533202 ] } },
{ "type": "Feature", "properties": { "id": 16 }, "geometry": { "type": "Point", "coordinates": [ -84.13625126603344, 9.921809631569024 ] } },
{ "type": "Feature", "properties": { "id": 21 }, "geometry": { "type": "Point", "coordinates": [ -84.130343291077992, 9.902374942429324 ] } },
{ "type": "Feature", "properties": { "id": 20 }, "geometry": { "type": "Point", "coordinates": [ -84.136660943128874, 9.905008781972358 ] } },
{ "type": "Feature", "properties": { "id": 23 }, "geometry": { "type": "Point", "coordinates": [ -84.135679874295036, 9.924528272155927 ] } },
{ "type": "Feature", "properties": { "id": 22 }, "geometry": { "type": "Point", "coordinates": [ -84.136229704081032, 9.923083997154027 ] } },
{ "type": "Feature", "properties": { "id": 25 }, "geometry": { "type": "Point", "coordinates": [ -84.152314920565473, 9.946584532924019 ] } },
{ "type": "Feature", "properties": { "id": 24 }, "geometry": { "type": "Point", "coordinates": [ -84.148002530087041, 9.943653695199469 ] } },
{ "type": "Feature", "properties": { "id": 27 }, "geometry": { "type": "Point", "coordinates": [ -84.136423720815486, 9.919213297480649 ] } },
{ "type": "Feature", "properties": { "id": 26 }, "geometry": { "type": "Point", "coordinates": [ -84.136429613015665, 9.920089718628928 ] } }
]
}
